ASD_GUI/ASD_GUI.py
ASD_GUI/__init__.py
ASD_GUI/ASD_Interactive/__init__.py
ASD_GUI/ASD_Interactive/interactiveASD.py
ASD_GUI/Extras/__init__.py
ASD_GUI/Extras/preQ.py
ASD_GUI/Extras/nn_list_maker/__init__.py
ASD_GUI/Extras/nn_list_maker/create_neighbour_list.py
ASD_GUI/Extras/nn_list_maker/read_uppasd.py
ASD_GUI/Extras/nn_list_maker/structure.py
ASD_GUI/Input_Creator/ASDInputAux.py
ASD_GUI/Input_Creator/ASDInputGen.py
ASD_GUI/Input_Creator/__init__.py
ASD_GUI/Input_Creator/System_import/ASDImportSys.py
ASD_GUI/Input_Creator/System_import/SPRKKR_parser.py
ASD_GUI/Input_Creator/System_import/__init__.py
ASD_GUI/PLOT/ASDPlots2D.py
ASD_GUI/PLOT/ASDPlotsReading.py
ASD_GUI/PLOT/__init__.py
ASD_GUI/UI/ASDInputWindows.py
ASD_GUI/UI/ASDInteractiveTab.py
ASD_GUI/UI/ASDMenuToolbar.py
ASD_GUI/UI/ASDUIDriver.py
ASD_GUI/UI/ASD_Viz.ui
ASD_GUI/UI/DMfile_Creator.ui
ASD_GUI/UI/Error_Msg.ui
ASD_GUI/UI/Info_Msg.ui
ASD_GUI/UI/InitPhase_Creator.ui
ASD_GUI/UI/Jfile_Creator.ui
ASD_GUI/UI/Kfile_Creator.ui
ASD_GUI/UI/Momfile_Creator.ui
ASD_GUI/UI/Posfile_Creator.ui
ASD_GUI/UI/Restart_Creator.ui
ASD_GUI/UI/__init__.py
ASD_GUI/VTK_Viz/ASDVTKEneActors.py
ASD_GUI/VTK_Viz/ASDVTKGenActors.py
ASD_GUI/VTK_Viz/ASDVTKMomActors.py
ASD_GUI/VTK_Viz/ASDVTKNeighActors.py
ASD_GUI/VTK_Viz/ASDVTKReading.py
ASD_GUI/VTK_Viz/ASDVTKVizOptions.py
ASD_GUI/VTK_Viz/__init__.py
asd_gui-1.5.0.dist-info/METADATA
asd_gui-1.5.0.dist-info/WHEEL
asd_gui-1.5.0.dist-info/entry_points.txt
asd_gui-1.5.0.dist-info/top_level.txt
asd_gui-1.5.0.dist-info/RECORD
