Metadata-Version: 2.1
Name: asd_gui
Version: 1.5.0
Summary: The UppASD GUI
Author-email: "Jonathan P. Chico" <uppasd@physics.uu.se>
License: GPL-3.0-or-later
Project-URL: Homepage, https://github.com/UppASD/UppASD
Requires-Python: >=3.6
Requires-Dist: matplotlib
Requires-Dist: numpy >=1.19.0
Requires-Dist: pandas
Requires-Dist: PyQt6
Requires-Dist: PyYAML
Requires-Dist: setuptools
Requires-Dist: vtk >=9.0.0
Requires-Dist: spglib
